_pyapsi.cpython-310-x86_64-linux-gnu.so
tests/__init__.py
tests/utils_test.py
tests/conftest.py
tests/integration_test.py
apsi/clients.py
apsi/__init__.py
apsi/utils.py
apsi/servers.py
apsi-0.1.2.dist-info/WHEEL
apsi-0.1.2.dist-info/top_level.txt
apsi-0.1.2.dist-info/LICENSE
apsi-0.1.2.dist-info/METADATA
apsi-0.1.2.dist-info/RECORD
