Metadata-Version: 2.1
Name: apsi
Version: 0.1.2
Summary: Python wrapper for labeled and unlabeled asynchronous private set intersection (APSI).
Home-page: https://github.com/LGro/PyAPSI
Author: Lukas Grossberger
Author-email: code@grossberger.xyz
License: UNKNOWN
Platform: UNKNOWN
Classifier: Development Status :: 4 - Beta
Classifier: Intended Audience :: Developers
Classifier: Topic :: Utilities
Classifier: License :: OSI Approved :: MIT License
Classifier: Natural Language :: English
Classifier: Operating System :: POSIX :: Linux
Classifier: Programming Language :: Python :: 3 :: Only
Classifier: Programming Language :: Python :: 3.8
Classifier: Programming Language :: Python :: 3.9
Classifier: Programming Language :: Python :: 3.10
Classifier: Typing :: Typed
Requires-Python: >=3.8,<3.11
License-File: LICENSE
Provides-Extra: test
Requires-Dist: pytest ; extra == 'test'
